jupyterlab_bookmarks_extension/__init__.py
jupyterlab_bookmarks_extension/_version.py
jupyterlab_bookmarks_extension/handlers.py
jupyterlab_bookmarks_extension/labextension/jupyterlab-bookmarks-extension-0.3.0.tgz
jupyterlab_bookmarks_extension/labextension/jupyterlab-bookmarks-extension-0.5.0.tgz
jupyterlab_bookmarks_extension/labextension/jupyterlab-bookmarks-extension-0.5.1.tgz
jupyterlab_bookmarks_extension/labextension/jupyterlab-bookmarks-extension-0.5.2.tgz
jupyterlab_bookmarks_extension/labextension/jupyterlab-bookmarks-extension-0.5.3.tgz
jupyterlab_bookmarks_extension/labextension/jupyterlab-bookmarks-extension-0.5.4.tgz
jupyterlab_bookmarks_extension/labextension/jupyterlab-bookmarks-extension-0.5.5.tgz
jupyterlab_bookmarks_extension/labextension/jupyterlab-bookmarks-extension-0.5.6.tgz
jupyterlab_bookmarks_extension-0.5.6.data/data/etc/jupyter/jupyter_notebook_config.d/jupyterlab_bookmarks_extension.json
jupyterlab_bookmarks_extension-0.5.6.data/data/share/jupyter/lab/extensions/jupyterlab-bookmarks-extension-0.5.6.tgz
jupyterlab_bookmarks_extension-0.5.6.dist-info/LICENSE
jupyterlab_bookmarks_extension-0.5.6.dist-info/METADATA
jupyterlab_bookmarks_extension-0.5.6.dist-info/WHEEL
jupyterlab_bookmarks_extension-0.5.6.dist-info/top_level.txt
jupyterlab_bookmarks_extension-0.5.6.dist-info/RECORD
