Metadata-Version: 2.1
Name: jupyterlab-bookmarks-extension
Version: 0.5.6
Summary: A JupyterLab extension to provide Launcher icons for favorites. Allows 'bookmarking' files for quick access from the Launcher.
Home-page: https://github.com/nandor-poka/jupyterlab-bookmarks-extension
Author: Dr. Nandor Poka
License: BSD-3-Clause
Keywords: Jupyter,JupyterLab
Platform: Linux
Platform: Mac OS X
Platform: Windows
Classifier: License :: OSI Approved :: BSD License
Classifier: Programming Language :: Python
Classifier: Programming Language :: Python :: 3
Classifier: Programming Language :: Python :: 3.5
Classifier: Programming Language :: Python :: 3.6
Classifier: Programming Language :: Python :: 3.7
Classifier: Programming Language :: Python :: 3.8
Classifier: Framework :: Jupyter
Requires-Dist: jupyterlab (~=2.2.0)
